{
  "word": "eerie",
  "phonetic": "/\u02c8\u026a\u0259\u0279i/",
  "pronunciation": "https://api.dictionaryapi.dev/media/pronunciations/en/eerie-uk.mp3",
  "meanings": [
    {
      "word": "eerie",
      "part_of_speech": "adjective",
      "definition": "Strange, weird, fear-inspiring.",
      "example": "The eerie sounds seemed to come from the graveyard after midnight."
    },
    {
      "word": "eerie",
      "part_of_speech": "adjective",
      "definition": "Frightened, timid.",
      "example": "The horror movie was so gory that I had to look away."
    }
  ]
}